LICENSE
README.md
setup.cfg
setup.py
faps/__init__.py
faps/accuracy_paternity.py
faps/alogsumexp.py
faps/calculate_SNP_calls.py
faps/calculate_geno_probs.py
faps/convert_genotypes.py
faps/do_clustering.py
faps/draw_fathers.py
faps/effective_nloci.py
faps/export_to_colony.py
faps/genotypeArray.py
faps/incompatibilities.py
faps/lik_partition.py
faps/lik_sampled_fathers.py
faps/lik_unsampled_fathers.py
faps/make_generation.py
faps/make_offspring.py
faps/make_parents.py
faps/make_power.py
faps/make_sibships.py
faps/mating_events.py
faps/mating_summary.py
faps/pairwise_lik_fullsibs.py
faps/parent_index.py
faps/partition_accuracy.py
faps/paternityArray.py
faps/paternity_array.py
faps/paternity_list.py
faps/posterior_mating.py
faps/pr_transition.py
faps/pr_unsampled.py
faps/read_genotypes.py
faps/read_paternity_array.py
faps/relation_matrix.py
faps/sibshipCluster.py
faps/sibship_clustering.py
faps/sibship_partitions.py
faps/sibship_paternity.py
faps/sibship_transitions.py
faps/squash_siblings.py
faps/summarise_paternity.py
faps/summarise_sires.py
faps/transition_probability.py
faps/unique_rows.py
faps.egg-info/PKG-INFO
faps.egg-info/SOURCES.txt
faps.egg-info/dependency_links.txt
faps.egg-info/not-zip-safe
faps.egg-info/requires.txt
faps.egg-info/top_level.txt
tests/test_clustering.py
tests/test_draw_fathers.py
tests/test_genotypeArray.py
tests/test_paternityArray.py
tests/test_paternity_array.py
tests/test_simulate_mating.py
tests/test_transition_probabilities.py