Metadata-Version: 2.1
Name: faps
Version: 2.8.1
Summary:  Inference of paternity and sibling relationships accounting for uncertainty in genealogy
Home-page: http://github.com/ellisztamas/faps
Author: Tom Ellis
Author-email: thomas.ellis@gmi.oeaw.ac.at
License: MIT
License-File: LICENSE
Requires-Dist: numpy
Requires-Dist: scipy
Requires-Dist: pandas
Requires-Dist: tqdm
